setup.py
gbdistribution.egg-info/PKG-INFO
gbdistribution.egg-info/SOURCES.txt
gbdistribution.egg-info/dependency_links.txt
gbdistribution.egg-info/not-zip-safe
gbdistribution.egg-info/top_level.txt
gbdistributions/Binomialdistribution.py
gbdistributions/Gaussiandistribution.py
gbdistributions/Generaldistribution.py
gbdistributions/__init__.py