Metadata-Version: 1.0
Name: gbdistribution
Version: 0.1
Summary: Gaussian and Binomial distributions
Home-page: UNKNOWN
Author: SowmiyaNarayanan G
Author-email: UNKNOWN
License: UNKNOWN
Platform: UNKNOWN
